spicelab/__init__.py
spicelab/doctor.py
spicelab/orchestrator.py
spicelab/py.typed
spicelab/analysis/__init__.py
spicelab/analysis/measure.py
spicelab/analysis/montecarlo.py
spicelab/analysis/pipeline.py
spicelab/analysis/result.py
spicelab/analysis/signal.py
spicelab/analysis/sweep_grid.py
spicelab/analysis/viz/plot.py
spicelab/cli/__init__.py
spicelab/cli/measure.py
spicelab/core/__init__.py
spicelab/core/adc.py
spicelab/core/circuit.py
spicelab/core/components.py
spicelab/core/net.py
spicelab/core/types.py
spicelab/core/typing.py
spicelab/dsl/__init__.py
spicelab/dsl/builder.py
spicelab/dsl/flow.py
spicelab/dsl/schematic.py
spicelab/engines/__init__.py
spicelab/engines/base.py
spicelab/engines/directives.py
spicelab/engines/exceptions.py
spicelab/engines/factory.py
spicelab/engines/ltspice.py
spicelab/engines/ltspice_cli.py
spicelab/engines/ngspice.py
spicelab/engines/ngspice_proc.py
spicelab/engines/ngspice_shared.py
spicelab/engines/orchestrator.py
spicelab/engines/result.py
spicelab/engines/xyce.py
spicelab/engines/xyce_cli.py
spicelab/extensions/__init__.py
spicelab/extensions/adc.py
spicelab/io/__init__.py
spicelab/io/log_reader.py
spicelab/io/ltspice_asc.py
spicelab/io/ltspice_parser.py
spicelab/io/raw_reader.py
spicelab/io/readers.py
spicelab/io/spice_parser.py
spicelab/library/__init__.py
spicelab/library/capacitors.py
spicelab/library/diodes.py
spicelab/library/factory_typing.py
spicelab/library/importers.py
spicelab/library/inductors.py
spicelab/library/metadata.py
spicelab/library/opamps.py
spicelab/library/registry.py
spicelab/library/resistors.py
spicelab/library/switches.py
spicelab/library/transistors.py
spicelab/library/utils.py
spicelab/library/data/opamps/lm741.sub
spicelab/library/data/opamps/tl081.sub
spicelab/reporting/__init__.py
spicelab/reporting/report.py
spicelab/spice/__init__.py
spicelab/spice/base.py
spicelab/spice/ltspice_cli.py
spicelab/spice/ngspice_cli.py
spicelab/spice/ngspice_shared.py
spicelab/spice/ngspice_shared_backend.py
spicelab-0.3.1.dist-info/licenses/LICENSE
spicelab-0.3.1.dist-info/METADATA
spicelab-0.3.1.dist-info/WHEEL
spicelab-0.3.1.dist-info/entry_points.txt
spicelab-0.3.1.dist-info/top_level.txt
spicelab-0.3.1.dist-info/RECORD
