Metadata-Version: 2.4
Name: spicelab
Version: 0.3.1
Summary: Circuit Toolkit (package: spicelab) – typed SPICE orchestration, sweeps, and Monte Carlo.
Author: Luiz Carlos Gili
License: MIT
Project-URL: Homepage, https://github.com/lgili/circuit_toolkit
Project-URL: Repository, https://github.com/lgili/circuit_toolkit.git
Project-URL: Issues, https://github.com/lgili/circuit_toolkit/issues
Project-URL: Documentation, https://lgili.github.io/CircuitToolkit/
Keywords: spice,circuit,simulation,ngspice,electronics
Classifier: Development Status :: 3 - Alpha
Classifier: Intended Audience :: Science/Research
Classifier: License :: OSI Approved :: MIT License
Classifier: Programming Language :: Python :: 3
Classifier: Programming Language :: Python :: 3.10
Classifier: Programming Language :: Python :: 3.11
Classifier: Programming Language :: Python :: 3.12
Classifier: Topic :: Scientific/Engineering
Classifier: Topic :: Scientific/Engineering :: Electronic Design Automation (EDA)
Requires-Python: >=3.10
License-File: LICENSE
Requires-Dist: numpy>=1.26
Requires-Dist: pandas>=2.1
Requires-Dist: polars>=1.33.1
Requires-Dist: typing-extensions>=4.9
Requires-Dist: xarray>=2025.6.1
Requires-Dist: pydantic>=2.7
Provides-Extra: opt
Requires-Dist: scipy>=1.12; extra == "opt"
Provides-Extra: viz
Requires-Dist: plotly>=5.20; extra == "viz"
Requires-Dist: kaleido>=0.2.1; extra == "viz"
Requires-Dist: ipywidgets>=8.1; extra == "viz"
Requires-Dist: anywidget>=0.9; extra == "viz"
Requires-Dist: nbformat>=5.0; extra == "viz"
Provides-Extra: data
Requires-Dist: xarray>=2024.1; extra == "data"
Requires-Dist: polars>=1.6.0; extra == "data"
Provides-Extra: xarray
Requires-Dist: xarray>=2024.1; extra == "xarray"
Provides-Extra: polars
Requires-Dist: polars>=1.6.0; extra == "polars"
Dynamic: license-file
